LICENSE
README.rst
setup.py
pflog/__init__.py
pflog/__main__.py
pflog/data.py
pflog/pflog.py
pflog.egg-info/PKG-INFO
pflog.egg-info/SOURCES.txt
pflog.egg-info/dependency_links.txt
pflog.egg-info/entry_points.txt
pflog.egg-info/requires.txt
pflog.egg-info/top_level.txt
tests/test_example.py