Metadata-Version: 2.1
Name: pflog
Version: 1.0.8
Summary: A logger client that can speak to a pftel telemetry server
Home-page: https://github.com/FNNDSC/pflog
Author: FNNDSC
Author-email: rudolph.pienaar@childrens.harvard.edu
License: MIT
Platform: UNKNOWN
Classifier: License :: OSI Approved :: MIT License
Classifier: Topic :: Scientific/Engineering
Classifier: Topic :: Scientific/Engineering :: Bio-Informatics
Classifier: Topic :: Scientific/Engineering :: Medical Science Apps.
Provides-Extra: none
Provides-Extra: dev
License-File: LICENSE
